megaspark/__init__.py
megaspark/tomega.py
megaspark/case/__init__.py
megaspark/case/test.py
megaspark/ml/__init__.py
megaspark/ml/mega_xgboost.py
megaspark/ml/pipeline.py
megaspark/ml/util.py
megaspark/ml/xgboost.py
megaspark/sql/__init__.py
megaspark/sql/megaframe.py
mega_spark-1.1.1.dist-info/LICENSE
mega_spark-1.1.1.dist-info/METADATA
mega_spark-1.1.1.dist-info/WHEEL
mega_spark-1.1.1.dist-info/top_level.txt
mega_spark-1.1.1.dist-info/RECORD
