Metadata-Version: 2.1
Name: mega-spark
Version: 1.1.1
Summary: Some computing tools about feature tool and ml model.
Home-page: UNKNOWN
Author: huangning
License: UNKNOWN
Platform: UNKNOWN
Classifier: Programming Language :: Python :: 3
Classifier: License :: OSI Approved :: MIT License
Classifier: Operating System :: OS Independent
Requires-Python: >=2.7,<=3.7.*
Requires-Dist: pyspark (<2.4.7,>=2.4.0)
